odoo9_addon_l10n_es_cnae-9.0.1.0.0-py2.7-nspkg.pth
odoo9_addon_l10n_es_cnae-9.0.1.0.0.dist-info/top_level.txt
odoo9_addon_l10n_es_cnae-9.0.1.0.0.dist-info/WHEEL
odoo9_addon_l10n_es_cnae-9.0.1.0.0.dist-info/RECORD
odoo9_addon_l10n_es_cnae-9.0.1.0.0.dist-info/metadata.json
odoo9_addon_l10n_es_cnae-9.0.1.0.0.dist-info/DESCRIPTION.rst
odoo9_addon_l10n_es_cnae-9.0.1.0.0.dist-info/METADATA
odoo9_addon_l10n_es_cnae-9.0.1.0.0.dist-info/namespace_packages.txt
odoo_addons/l10n_es_cnae/__openerp__.py
odoo_addons/l10n_es_cnae/__init__.py
odoo_addons/l10n_es_cnae/README.rst
odoo_addons/l10n_es_cnae/i18n/es.po
odoo_addons/l10n_es_cnae/data/res.partner.category.csv
odoo_addons/l10n_es_cnae/static/description/icon.png
